[
  {
    "_id": "5e48184949744390d736bcf8",
    "index": 0,
    "guid": "c2110c14-7ec4-491e-aa82-6cacad07e4ef",
    "isActive": false,
    "balance": "$2,331.98",
    "picture": "http://placehold.it/32x32",
    "age": 36,
    "eyeColor": "green",
    "name": {
      "first": "Bolton",
      "last": "Estes"
    },
    "company": "STUCCO",
    "email": "bolton.estes@stucco.name",
    "phone": "+1 (997) 464-2224",
    "address": "155 Leonora Court, Chase, New Mexico, 4148",
    "about": "Eiusmod deserunt pariatur nostrud laboris duis laboris aliquip ea labore nisi elit. Et dolore velit do sint est sunt culpa commodo sint. Dolore consequat laboris qui non anim eu consectetur pariatur ullamco fugiat. Nulla adipisicing cillum eu ullamco consectetur sit incididunt exercitation. Nulla officia enim mollit veniam veniam incididunt nisi Lorem dolor. Mollit non dolore proident labore tempor dolore voluptate incididunt esse nisi cupidatat commodo qui.",
    "registered": "Wednesday, December 17, 2014 9:21 PM",
    "latitude": "77.578515",
    "longitude": "-63.882052",
    "tags": [
      "est",
      "laboris",
      "ex",
      "ipsum",
      "eiusmod"
    ],
    "range": [
      0,
      1,
      2,
      3,
      4,
      5,
      6,
      7,
      8,
      9
    ],
    "friends": [
      {
        "id": 0,
        "name": "Elinor Whitfield"
      },
      {
        "id": 1,
        "name": "Strong Morris"
      },
      {
        "id": 2,
        "name": "Julia Morin"
      }
    ],
    "greeting": "Hello, Bolton! You have 7 unread messages.",
    "favoriteFruit": "apple"
  },
  {
    "_id": "5e48184993651a2c5bfa81fb",
    "index": 1,
    "guid": "3a42bfe7-62ba-4706-8813-ed3d47973a9c",
    "isActive": true,
    "balance": "$3,412.59",
    "picture": "http://placehold.it/32x32",
    "age": 22,
    "eyeColor": "brown",
    "name": {
      "first": "French",
      "last": "Stanton"
    },
    "company": "COMFIRM",
    "email": "french.stanton@comfirm.tv",
    "phone": "+1 (951) 502-3665",
    "address": "782 Crown Street, Orason, Georgia, 3634",
    "about": "Anim commodo sit quis ad in et nulla laborum. Enim mollit nostrud cupidatat ad minim aliqua eu. Fugiat aute veniam laboris ullamco dolore consequat aliquip reprehenderit ipsum voluptate do. Cupidatat aliquip mollit in aliqua exercitation.",
    "registered": "Friday, February 14, 2020 4:07 PM",
    "latitude": "16.491164",
    "longitude": "19.820541",
    "tags": [
      "anim",
      "tempor",
      "ut",
      "velit",
      "nostrud"
    ],
    "range": [
      0,
      1,
      2,
      3,
      4,
      5,
      6,
      7,
      8,
      9
    ],
    "friends": [
      {
        "id": 0,
        "name": "Gloria Stout"
      },
      {
        "id": 1,
        "name": "Crosby Jimenez"
      },
      {
        "id": 2,
        "name": "Dickerson Ferguson"
      }
    ],
    "greeting": "Hello, French! You have 9 unread messages.",
    "favoriteFruit": "apple"
  },
  {
    "_id": "5e4818497545f932a02100c0",
    "index": 2,
    "guid": "81e937bc-4413-4956-a291-75aebf61b583",
    "isActive": true,
    "balance": "$3,482.83",
    "picture": "http://placehold.it/32x32",
    "age": 29,
    "eyeColor": "blue",
    "name": {
      "first": "Sheryl",
      "last": "Bradford"
    },
    "company": "WAAB",
    "email": "sheryl.bradford@waab.biz",
    "phone": "+1 (925) 440-2623",
    "address": "290 Huron Street, Roberts, New Hampshire, 2891",
    "about": "Adipisicing qui incididunt fugiat aute ex nisi sit incididunt ullamco labore aliquip elit quis anim. Nulla officia qui laborum consectetur labore Lorem et qui aliquip tempor sint reprehenderit velit. Ad ullamco commodo aliquip ut in incididunt.",
    "registered": "Tuesday, October 9, 2018 8:56 AM",
    "latitude": "71.621122",
    "longitude": "-58.079493",
    "tags": [
      "deserunt",
      "sint",
      "nulla",
      "laboris",
      "do"
    ],
    "range": [
      0,
      1,
      2,
      3,
      4,
      5,
      6,
      7,
      8,
      9
    ],
    "friends": [
      {
        "id": 0,
        "name": "May Underwood"
      },
      {
        "id": 1,
        "name": "Sellers Delgado"
      },
      {
        "id": 2,
        "name": "Haley Weber"
      }
    ],
    "greeting": "Hello, Sheryl! You have 5 unread messages.",
    "favoriteFruit": "banana"
  },
  {
    "_id": "5e481849f81464291e244c65",
    "index": 3,
    "guid": "a3fe25ed-8496-44ee-b458-9b5adf5bafe8",
    "isActive": true,
    "balance": "$2,768.21",
    "picture": "http://placehold.it/32x32",
    "age": 21,
    "eyeColor": "brown",
    "name": {
      "first": "Santana",
      "last": "Lane"
    },
    "company": "CUBIX",
    "email": "santana.lane@cubix.info",
    "phone": "+1 (826) 502-2479",
    "address": "840 Portland Avenue, Tioga, Alabama, 1908",
    "about": "Officia dolore velit qui ex. Dolore consectetur minim esse consectetur. Ut exercitation pariatur est anim consequat deserunt incididunt ipsum labore.",
    "registered": "Wednesday, August 27, 2014 5:13 PM",
    "latitude": "27.915619",
    "longitude": "81.312654",
    "tags": [
      "ullamco",
      "consequat",
      "nisi",
      "velit",
      "ea"
    ],
    "range": [
      0,
      1,
      2,
      3,
      4,
      5,
      6,
      7,
      8,
      9
    ],
    "friends": [
      {
        "id": 0,
        "name": "Meyers Kirk"
      },
      {
        "id": 1,
        "name": "Shana Velasquez"
      },
      {
        "id": 2,
        "name": "Brooks Moran"
      }
    ],
    "greeting": "Hello, Santana! You have 10 unread messages.",
    "favoriteFruit": "banana"
  },
  {
    "_id": "5e481849ff4a53a27a8a819c",
    "index": 4,
    "guid": "719495dd-245f-4fd6-af12-ebd02ab1f22e",
    "isActive": false,
    "balance": "$3,201.85",
    "picture": "http://placehold.it/32x32",
    "age": 33,
    "eyeColor": "brown",
    "name": {
      "first": "Barnett",
      "last": "Mcleod"
    },
    "company": "MEDIOT",
    "email": "barnett.mcleod@mediot.com",
    "phone": "+1 (978) 480-3018",
    "address": "548 Bartlett Place, Whitestone, Guam, 6741",
    "about": "Nisi ad occaecat pariatur consequat sunt ea. Duis consectetur ut ad labore proident velit eu commodo. Ut sit Lorem officia fugiat commodo do mollit in ad enim. Veniam do consectetur anim incididunt esse consequat eu.",
    "registered": "Tuesday, June 9, 2015 11:44 AM",
    "latitude": "85.94424",
    "longitude": "-27.441652",
    "tags": [
      "et",
      "ut",
      "incididunt",
      "do",
      "nulla"
    ],
    "range": [
      0,
      1,
      2,
      3,
      4,
      5,
      6,
      7,
      8,
      9
    ],
    "friends": [
      {
        "id": 0,
        "name": "Kelley Middleton"
      },
      {
        "id": 1,
        "name": "Silva Soto"
      },
      {
        "id": 2,
        "name": "Cindy Woodard"
      }
    ],
    "greeting": "Hello, Barnett! You have 8 unread messages.",
    "favoriteFruit": "banana"
  },
  {
    "_id": "5e481849748394cfd0361b8d",
    "index": 5,
    "guid": "4d344d95-2f66-4a53-9fe5-cdb9c34df932",
    "isActive": true,
    "balance": "$3,180.42",
    "picture": "http://placehold.it/32x32",
    "age": 20,
    "eyeColor": "blue",
    "name": {
      "first": "Warren",
      "last": "Downs"
    },
    "company": "XUMONK",
    "email": "warren.downs@xumonk.org",
    "phone": "+1 (881) 513-3915",
    "address": "400 Bennet Court, Grantville, Wisconsin, 4490",
    "about": "Tempor exercitation aute nulla tempor eu irure aliqua consectetur labore veniam proident sint laborum sunt. Esse nulla Lorem enim sint enim sunt commodo. Enim quis cillum ea cillum sint labore eiusmod pariatur sunt consequat dolor pariatur adipisicing. Nulla cupidatat est anim minim veniam Lorem sint Lorem.",
    "registered": "Wednesday, May 3, 2017 8:18 AM",
    "latitude": "-75.056924",
    "longitude": "158.826238",
    "tags": [
      "irure",
      "eiusmod",
      "eiusmod",
      "occaecat",
      "anim"
    ],
    "range": [
      0,
      1,
      2,
      3,
      4,
      5,
      6,
      7,
      8,
      9
    ],
    "friends": [
      {
        "id": 0,
        "name": "Ilene Kim"
      },
      {
        "id": 1,
        "name": "Cruz Lyons"
      },
      {
        "id": 2,
        "name": "Ingram Young"
      }
    ],
    "greeting": "Hello, Warren! You have 9 unread messages.",
    "favoriteFruit": "apple"
  },
  {
    "_id": "5e481849885da9fde5c0800f",
    "index": 6,
    "guid": "fa53b3bb-234c-4207-bf96-ab7db9f367e6",
    "isActive": true,
    "balance": "$1,740.32",
    "picture": "http://placehold.it/32x32",
    "age": 24,
    "eyeColor": "green",
    "name": {
      "first": "Conway",
      "last": "Hunt"
    },
    "company": "HALAP",
    "email": "conway.hunt@halap.io",
    "phone": "+1 (855) 401-3978",
    "address": "215 Belmont Avenue, Edenburg, New Jersey, 9361",
    "about": "Eiusmod cupidatat veniam incididunt voluptate incididunt nisi amet irure commodo quis. Tempor officia reprehenderit amet dolore esse cupidatat occaecat ipsum sint. Do nisi amet enim duis qui dolore. Excepteur aliquip laborum do velit ut anim nulla ut qui.",
    "registered": "Monday, May 16, 2016 9:10 AM",
    "latitude": "-89.757437",
    "longitude": "-137.472332",
    "tags": [
      "aute",
      "dolor",
      "ea",
      "excepteur",
      "deserunt"
    ],
    "range": [
      0,
      1,
      2,
      3,
      4,
      5,
      6,
      7,
      8,
      9
    ],
    "friends": [
      {
        "id": 0,
        "name": "Snow Hutchinson"
      },
      {
        "id": 1,
        "name": "Sharp Valencia"
      },
      {
        "id": 2,
        "name": "Lott Olsen"
      }
    ],
    "greeting": "Hello, Conway! You have 6 unread messages.",
    "favoriteFruit": "strawberry"
  },
  {
    "_id": "5e4818490f5e535748345665",
    "index": 7,
    "guid": "2a3e8df1-e711-4f70-a9e0-38c1e30e95d5",
    "isActive": true,
    "balance": "$1,536.08",
    "picture": "http://placehold.it/32x32",
    "age": 34,
    "eyeColor": "blue",
    "name": {
      "first": "Marlene",
      "last": "Malone"
    },
    "company": "UTARA",
    "email": "marlene.malone@utara.ca",
    "phone": "+1 (885) 499-2180",
    "address": "400 Voorhies Avenue, Oasis, American Samoa, 7031",
    "about": "Sint incididunt labore velit ipsum esse. Cupidatat nisi ad labore minim reprehenderit nisi veniam. Excepteur ullamco anim laboris consectetur Lorem in consectetur. Id irure tempor mollit veniam duis tempor deserunt voluptate nisi ex. Incididunt veniam elit excepteur reprehenderit culpa consequat aliqua aliquip occaecat est quis dolor consequat.",
    "registered": "Sunday, January 21, 2018 4:51 AM",
    "latitude": "-65.756466",
    "longitude": "26.139142",
    "tags": [
      "nulla",
      "culpa",
      "sit",
      "magna",
      "esse"
    ],
    "range": [
      0,
      1,
      2,
      3,
      4,
      5,
      6,
      7,
      8,
      9
    ],
    "friends": [
      {
        "id": 0,
        "name": "Ratliff Wright"
      },
      {
        "id": 1,
        "name": "Amanda Freeman"
      },
      {
        "id": 2,
        "name": "Zelma Morrow"
      }
    ],
    "greeting": "Hello, Marlene! You have 9 unread messages.",
    "favoriteFruit": "banana"
  },
  {
    "_id": "5e481849134f96a3a4e173c5",
    "index": 8,
    "guid": "5882e32d-1143-4ffe-b396-054261dee83b",
    "isActive": false,
    "balance": "$3,897.28",
    "picture": "http://placehold.it/32x32",
    "age": 24,
    "eyeColor": "brown",
    "name": {
      "first": "Francisca",
      "last": "Fry"
    },
    "company": "SPACEWAX",
    "email": "francisca.fry@spacewax.me",
    "phone": "+1 (995) 576-3875",
    "address": "945 Bond Street, Barronett, West Virginia, 2212",
    "about": "Laborum eu labore tempor eiusmod commodo aliqua nulla laborum laboris. Deserunt sint cillum ad consectetur occaecat tempor occaecat exercitation quis ad proident velit irure. Cupidatat ut anim ut pariatur deserunt Lorem consectetur et exercitation dolor voluptate. Reprehenderit laborum reprehenderit amet tempor quis id. Aliquip occaecat dolore amet sunt sunt deserunt officia veniam mollit nulla dolore id esse eiusmod.",
    "registered": "Wednesday, July 19, 2017 7:32 PM",
    "latitude": "-3.637894",
    "longitude": "10.637667",
    "tags": [
      "aliqua",
      "ut",
      "consequat",
      "non",
      "eiusmod"
    ],
    "range": [
      0,
      1,
      2,
      3,
      4,
      5,
      6,
      7,
      8,
      9
    ],
    "friends": [
      {
        "id": 0,
        "name": "Hale Hoffman"
      },
      {
        "id": 1,
        "name": "Morse Rowe"
      },
      {
        "id": 2,
        "name": "Aileen Lowe"
      }
    ],
    "greeting": "Hello, Francisca! You have 9 unread messages.",
    "favoriteFruit": "strawberry"
  },
  {
    "_id": "5e481849595baec9204469db",
    "index": 9,
    "guid": "29f53831-f5cc-4b2d-9568-b62007682edd",
    "isActive": true,
    "balance": "$1,340.10",
    "picture": "http://placehold.it/32x32",
    "age": 28,
    "eyeColor": "green",
    "name": {
      "first": "Woodard",
      "last": "Hoover"
    },
    "company": "PORTALINE",
    "email": "woodard.hoover@portaline.net",
    "phone": "+1 (911) 408-3181",
    "address": "956 Classon Avenue, Cassel, Nevada, 2164",
    "about": "Est nisi nostrud exercitation anim occaecat id tempor dolore pariatur. Aliqua quis occaecat nostrud laboris in laborum aliqua aliqua. Laboris labore laboris nulla id proident incididunt mollit incididunt reprehenderit do excepteur consectetur. Lorem cillum proident et qui quis aute elit reprehenderit. Cillum anim sint nostrud fugiat sint culpa est quis adipisicing sit. Excepteur commodo minim excepteur commodo voluptate.",
    "registered": "Monday, August 3, 2015 6:11 AM",
    "latitude": "14.483653",
    "longitude": "8.039226",
    "tags": [
      "dolore",
      "commodo",
      "proident",
      "enim",
      "sunt"
    ],
    "range": [
      0,
      1,
      2,
      3,
      4,
      5,
      6,
      7,
      8,
      9
    ],
    "friends": [
      {
        "id": 0,
        "name": "Schmidt Black"
      },
      {
        "id": 1,
        "name": "Bowman Valenzuela"
      },
      {
        "id": 2,
        "name": "Carpenter Clark"
      }
    ],
    "greeting": "Hello, Woodard! You have 6 unread messages.",
    "favoriteFruit": "apple"
  },
  {
    "_id": "5e481849b436128a73b3fe19",
    "index": 10,
    "guid": "26c3ec66-c0b7-4932-89de-c3737e1f7d9e",
    "isActive": false,
    "balance": "$1,025.52",
    "picture": "http://placehold.it/32x32",
    "age": 27,
    "eyeColor": "green",
    "name": {
      "first": "Giles",
      "last": "Jackson"
    },
    "company": "GAPTEC",
    "email": "giles.jackson@gaptec.co.uk",
    "phone": "+1 (974) 483-2493",
    "address": "875 Hendrix Street, Indio, Minnesota, 4288",
    "about": "Commodo eiusmod deserunt officia eiusmod labore aute. Pariatur aute velit eiusmod eiusmod esse esse laborum deserunt sit Lorem adipisicing in veniam adipisicing. Aliqua ex aute deserunt laborum amet eiusmod velit velit voluptate anim minim non sit do. Labore enim officia aliqua veniam qui eiusmod qui exercitation id qui consequat.",
    "registered": "Monday, December 8, 2014 7:06 AM",
    "latitude": "-74.150977",
    "longitude": "-109.689615",
    "tags": [
      "pariatur",
      "velit",
      "proident",
      "reprehenderit",
      "cupidatat"
    ],
    "range": [
      0,
      1,
      2,
      3,
      4,
      5,
      6,
      7,
      8,
      9
    ],
    "friends": [
      {
        "id": 0,
        "name": "Lakeisha Strong"
      },
      {
        "id": 1,
        "name": "Heath Hale"
      },
      {
        "id": 2,
        "name": "Abby Nielsen"
      }
    ],
    "greeting": "Hello, Giles! You have 8 unread messages.",
    "favoriteFruit": "apple"
  },
  {
    "_id": "5e4818499b6f37e07e512f9d",
    "index": 11,
    "guid": "aeb1f2b7-a312-4fd8-9bd9-ee98ef5b509b",
    "isActive": true,
    "balance": "$2,571.59",
    "picture": "http://placehold.it/32x32",
    "age": 27,
    "eyeColor": "brown",
    "name": {
      "first": "Elliott",
      "last": "Horne"
    },
    "company": "VENOFLEX",
    "email": "elliott.horne@venoflex.biz",
    "phone": "+1 (891) 518-2002",
    "address": "959 Pilling Street, Talpa, Virginia, 6295",
    "about": "Laborum laborum tempor duis ad aute sit nostrud irure adipisicing consectetur labore cupidatat. Dolore officia ea velit enim. Dolore ut veniam consequat proident reprehenderit labore voluptate. Aute dolore velit do nisi cupidatat Lorem nostrud adipisicing veniam. Dolor fugiat quis do ea pariatur magna sit culpa laborum ut magna. Elit occaecat mollit laborum exercitation sunt in cillum do tempor laboris laborum ullamco ut sint.",
    "registered": "Friday, February 7, 2020 8:41 AM",
    "latitude": "23.136038",
    "longitude": "-77.561327",
    "tags": [
      "tempor",
      "enim",
      "quis",
      "ullamco",
      "culpa"
    ],
    "range": [
      0,
      1,
      2,
      3,
      4,
      5,
      6,
      7,
      8,
      9
    ],
    "friends": [
      {
        "id": 0,
        "name": "Dolly Buckner"
      },
      {
        "id": 1,
        "name": "Cherie Coffey"
      },
      {
        "id": 2,
        "name": "Sally Mccray"
      }
    ],
    "greeting": "Hello, Elliott! You have 7 unread messages.",
    "favoriteFruit": "strawberry"
  },
  {
    "_id": "5e481849664fbdc4ea9d0120",
    "index": 12,
    "guid": "5da1e822-8301-4d1d-bd0a-e44ea5c026e0",
    "isActive": true,
    "balance": "$1,743.98",
    "picture": "http://placehold.it/32x32",
    "age": 26,
    "eyeColor": "brown",
    "name": {
      "first": "Owen",
      "last": "Strickland"
    },
    "company": "ENDICIL",
    "email": "owen.strickland@endicil.name",
    "phone": "+1 (896) 470-3581",
    "address": "400 Imlay Street, Mammoth, Puerto Rico, 2632",
    "about": "Veniam sit ullamco voluptate qui voluptate deserunt deserunt quis exercitation labore. Culpa dolor cillum minim esse cupidatat nisi. Ullamco consectetur id do incididunt et cupidatat eiusmod reprehenderit enim. Cillum ullamco ullamco labore labore Lorem esse aute elit. Nostrud nisi officia culpa incididunt id enim aliquip veniam et culpa quis est quis cupidatat.",
    "registered": "Friday, December 13, 2019 5:47 AM",
    "latitude": "75.350257",
    "longitude": "46.73742",
    "tags": [
      "ex",
      "sunt",
      "elit",
      "eu",
      "sit"
    ],
    "range": [
      0,
      1,
      2,
      3,
      4,
      5,
      6,
      7,
      8,
      9
    ],
    "friends": [
      {
        "id": 0,
        "name": "Melton Trevino"
      },
      {
        "id": 1,
        "name": "Patrick Coleman"
      },
      {
        "id": 2,
        "name": "Mcconnell Blanchard"
      }
    ],
    "greeting": "Hello, Owen! You have 5 unread messages.",
    "favoriteFruit": "apple"
  },
  {
    "_id": "5e481849b9dafba89a45d9f0",
    "index": 13,
    "guid": "cbcbadc5-c697-470f-9f13-5eb1ac512f7a",
    "isActive": false,
    "balance": "$1,971.85",
    "picture": "http://placehold.it/32x32",
    "age": 38,
    "eyeColor": "blue",
    "name": {
      "first": "Jennifer",
      "last": "Reynolds"
    },
    "company": "REALYSIS",
    "email": "jennifer.reynolds@realysis.tv",
    "phone": "+1 (911) 532-3126",
    "address": "962 Stryker Street, Loveland, Louisiana, 3205",
    "about": "Tempor cillum nisi consectetur amet deserunt pariatur eiusmod. Est non voluptate exercitation mollit adipisicing duis eu. Labore amet esse dolor tempor culpa aliqua.",
    "registered": "Tuesday, March 18, 2014 11:34 PM",
    "latitude": "28.688272",
    "longitude": "60.390259",
    "tags": [
      "in",
      "reprehenderit",
      "irure",
      "cupidatat",
      "commodo"
    ],
    "range": [
      0,
      1,
      2,
      3,
      4,
      5,
      6,
      7,
      8,
      9
    ],
    "friends": [
      {
        "id": 0,
        "name": "Joyce Hall"
      },
      {
        "id": 1,
        "name": "Murphy Harvey"
      },
      {
        "id": 2,
        "name": "Dionne Stevenson"
      }
    ],
    "greeting": "Hello, Jennifer! You have 5 unread messages.",
    "favoriteFruit": "banana"
  },
  {
    "_id": "5e481849a0ac4a114b86fcfe",
    "index": 14,
    "guid": "a13152f4-b82e-4f24-a792-c1fc24da6e3d",
    "isActive": true,
    "balance": "$1,156.32",
    "picture": "http://placehold.it/32x32",
    "age": 26,
    "eyeColor": "green",
    "name": {
      "first": "Winters",
      "last": "Chandler"
    },
    "company": "RONELON",
    "email": "winters.chandler@ronelon.biz",
    "phone": "+1 (880) 533-3882",
    "address": "146 Dumont Avenue, Century, South Dakota, 6710",
    "about": "Irure eiusmod excepteur commodo cupidatat. Nisi id cupidatat nulla esse ullamco excepteur culpa. Non pariatur reprehenderit ea eu mollit veniam mollit in amet id pariatur. Occaecat commodo duis ex fugiat et magna. Minim sint sit tempor fugiat.",
    "registered": "Thursday, September 11, 2014 6:22 AM",
    "latitude": "-32.718964",
    "longitude": "-94.751115",
    "tags": [
      "veniam",
      "ullamco",
      "anim",
      "ex",
      "tempor"
    ],
    "range": [
      0,
      1,
      2,
      3,
      4,
      5,
      6,
      7,
      8,
      9
    ],
    "friends": [
      {
        "id": 0,
        "name": "Griffin Arnold"
      },
      {
        "id": 1,
        "name": "Kirk Lambert"
      },
      {
        "id": 2,
        "name": "Shaw Pace"
      }
    ],
    "greeting": "Hello, Winters! You have 9 unread messages.",
    "favoriteFruit": "strawberry"
  },
  {
    "_id": "5e48184965e2982dba232f0f",
    "index": 15,
    "guid": "207991a8-cb9b-45ff-b9d8-9adc518e0288",
    "isActive": false,
    "balance": "$3,089.69",
    "picture": "http://placehold.it/32x32",
    "age": 29,
    "eyeColor": "green",
    "name": {
      "first": "Cortez",
      "last": "Mullins"
    },
    "company": "NAMEGEN",
    "email": "cortez.mullins@namegen.info",
    "phone": "+1 (820) 521-2724",
    "address": "471 President Street, Omar, Illinois, 3674",
    "about": "Exercitation mollit occaecat elit aute elit adipisicing elit amet cupidatat fugiat cillum dolor quis. Anim est elit duis ut. Amet id velit labore aute. In eu nostrud ipsum pariatur commodo ullamco ex do laborum incididunt. Id anim quis est sunt velit ea ad pariatur cupidatat in sunt ullamco fugiat duis. Ipsum anim amet voluptate ex magna est excepteur aliqua labore occaecat exercitation labore labore.",
    "registered": "Saturday, July 7, 2018 9:26 AM",
    "latitude": "65.327472",
    "longitude": "-86.944723",
    "tags": [
      "enim",
      "ad",
      "ipsum",
      "labore",
      "qui"
    ],
    "range": [
      0,
      1,
      2,
      3,
      4,
      5,
      6,
      7,
      8,
      9
    ],
    "friends": [
      {
        "id": 0,
        "name": "Francis Mccarty"
      },
      {
        "id": 1,
        "name": "Elisa Jennings"
      },
      {
        "id": 2,
        "name": "Anna Rodriguez"
      }
    ],
    "greeting": "Hello, Cortez! You have 9 unread messages.",
    "favoriteFruit": "apple"
  },
  {
    "_id": "5e481849d2d8b612797c9f06",
    "index": 16,
    "guid": "e21e2a8f-5732-4414-80a1-cbcafefc15ef",
    "isActive": true,
    "balance": "$2,100.70",
    "picture": "http://placehold.it/32x32",
    "age": 23,
    "eyeColor": "green",
    "name": {
      "first": "Pierce",
      "last": "Bell"
    },
    "company": "ECSTASIA",
    "email": "pierce.bell@ecstasia.com",
    "phone": "+1 (808) 442-2080",
    "address": "596 Linden Street, Wacissa, California, 8547",
    "about": "Elit ad cupidatat excepteur Lorem et do magna elit pariatur culpa duis eu elit aute. Officia eu duis est et adipisicing aliqua ad cillum anim mollit sint id ipsum. Tempor eiusmod aliqua elit laboris exercitation tempor cillum esse nulla irure exercitation Lorem. Irure proident ullamco commodo ea cupidatat aliqua voluptate incididunt aute. Laboris irure ex pariatur fugiat. Culpa consectetur esse incididunt nisi officia magna nostrud in dolore esse.",
    "registered": "Friday, August 16, 2019 7:06 AM",
    "latitude": "7.560286",
    "longitude": "-167.393739",
    "tags": [
      "in",
      "anim",
      "eiusmod",
      "qui",
      "qui"
    ],
    "range": [
      0,
      1,
      2,
      3,
      4,
      5,
      6,
      7,
      8,
      9
    ],
    "friends": [
      {
        "id": 0,
        "name": "Beard Schneider"
      },
      {
        "id": 1,
        "name": "Yesenia Mcintyre"
      },
      {
        "id": 2,
        "name": "Colon Walton"
      }
    ],
    "greeting": "Hello, Pierce! You have 9 unread messages.",
    "favoriteFruit": "banana"
  },
  {
    "_id": "5e481849ca21a05cbd70cd92",
    "index": 17,
    "guid": "fe7300cd-5890-487d-a939-670e7c4170c2",
    "isActive": true,
    "balance": "$1,815.77",
    "picture": "http://placehold.it/32x32",
    "age": 28,
    "eyeColor": "blue",
    "name": {
      "first": "Kelly",
      "last": "Jenkins"
    },
    "company": "SHOPABOUT",
    "email": "kelly.jenkins@shopabout.org",
    "phone": "+1 (957) 599-2699",
    "address": "424 Havens Place, Kenwood, Nebraska, 4386",
    "about": "Sunt esse magna aute minim id Lorem pariatur cupidatat deserunt. Dolor mollit reprehenderit elit nostrud. Sint mollit veniam sit sit anim ut do.",
    "registered": "Thursday, March 28, 2019 9:45 AM",
    "latitude": "-86.160014",
    "longitude": "117.947861",
    "tags": [
      "dolore",
      "qui",
      "pariatur",
      "adipisicing",
      "eiusmod"
    ],
    "range": [
      0,
      1,
      2,
      3,
      4,
      5,
      6,
      7,
      8,
      9
    ],
    "friends": [
      {
        "id": 0,
        "name": "Nora Justice"
      },
      {
        "id": 1,
        "name": "Bell Aguirre"
      },
      {
        "id": 2,
        "name": "Trevino Ballard"
      }
    ],
    "greeting": "Hello, Kelly! You have 10 unread messages.",
    "favoriteFruit": "strawberry"
  },
  {
    "_id": "5e481849e7fe31c7e18d746b",
    "index": 18,
    "guid": "d873202f-9da9-4314-b3d9-3400f9357448",
    "isActive": true,
    "balance": "$1,196.95",
    "picture": "http://placehold.it/32x32",
    "age": 37,
    "eyeColor": "green",
    "name": {
      "first": "Weeks",
      "last": "Bradshaw"
    },
    "company": "CINESANCT",
    "email": "weeks.bradshaw@cinesanct.io",
    "phone": "+1 (913) 474-3934",
    "address": "555 Durland Place, Gorham, Massachusetts, 739",
    "about": "Ad enim qui duis aliquip dolor nulla labore nulla aliqua. Sit in fugiat ipsum veniam nostrud do adipisicing nisi tempor. Amet excepteur minim laboris labore nulla elit.",
    "registered": "Friday, June 3, 2016 5:50 AM",
    "latitude": "-9.670364",
    "longitude": "24.857619",
    "tags": [
      "exercitation",
      "nisi",
      "ea",
      "exercitation",
      "laborum"
    ],
    "range": [
      0,
      1,
      2,
      3,
      4,
      5,
      6,
      7,
      8,
      9
    ],
    "friends": [
      {
        "id": 0,
        "name": "Fields Roman"
      },
      {
        "id": 1,
        "name": "Cara Harrington"
      },
      {
        "id": 2,
        "name": "Adrienne Doyle"
      }
    ],
    "greeting": "Hello, Weeks! You have 7 unread messages.",
    "favoriteFruit": "strawberry"
  },
  {
    "_id": "5e481849d0223ff821e012d1",
    "index": 19,
    "guid": "1cfcf5e9-7aca-4924-a56b-65ee54ffca39",
    "isActive": true,
    "balance": "$1,133.65",
    "picture": "http://placehold.it/32x32",
    "age": 28,
    "eyeColor": "brown",
    "name": {
      "first": "Bridges",
      "last": "Becker"
    },
    "company": "EQUITAX",
    "email": "bridges.becker@equitax.ca",
    "phone": "+1 (913) 576-2721",
    "address": "646 Kansas Place, Clarence, Michigan, 4595",
    "about": "Commodo cillum amet aute aute amet. Aliqua sunt excepteur adipisicing nisi aliquip. Cillum velit incididunt ipsum do proident duis non veniam minim non minim aute non.",
    "registered": "Thursday, March 8, 2018 9:33 AM",
    "latitude": "89.878293",
    "longitude": "-54.188736",
    "tags": [
      "dolore",
      "duis",
      "exercitation",
      "ea",
      "commodo"
    ],
    "range": [
      0,
      1,
      2,
      3,
      4,
      5,
      6,
      7,
      8,
      9
    ],
    "friends": [
      {
        "id": 0,
        "name": "Williams Hebert"
      },
      {
        "id": 1,
        "name": "Katrina Blake"
      },
      {
        "id": 2,
        "name": "Morales Patel"
      }
    ],
    "greeting": "Hello, Bridges! You have 8 unread messages.",
    "favoriteFruit": "banana"
  },
  {
    "_id": "5e481849dc19e792a196f89c",
    "index": 20,
    "guid": "e0f6ece3-b946-4de8-a244-063eaad90cfc",
    "isActive": true,
    "balance": "$1,418.34",
    "picture": "http://placehold.it/32x32",
    "age": 30,
    "eyeColor": "green",
    "name": {
      "first": "Potts",
      "last": "Sawyer"
    },
    "company": "STELAECOR",
    "email": "potts.sawyer@stelaecor.me",
    "phone": "+1 (977) 536-2265",
    "address": "624 Elliott Place, Brambleton, Northern Mariana Islands, 4474",
    "about": "Magna sit veniam ipsum consequat tempor sit ad cupidatat ex non. Ea elit Lorem minim sint quis consequat nisi occaecat. Enim anim qui elit ut labore eu nisi et et exercitation esse et. Pariatur consequat id nostrud irure incididunt. Id laboris duis proident non sint.",
    "registered": "Monday, October 14, 2019 7:41 PM",
    "latitude": "-17.583516",
    "longitude": "-35.885551",
    "tags": [
      "ea",
      "id",
      "do",
      "duis",
      "ut"
    ],
    "range": [
      0,
      1,
      2,
      3,
      4,
      5,
      6,
      7,
      8,
      9
    ],
    "friends": [
      {
        "id": 0,
        "name": "Moses Rosales"
      },
      {
        "id": 1,
        "name": "Floyd Foster"
      },
      {
        "id": 2,
        "name": "Ayala Sears"
      }
    ],
    "greeting": "Hello, Potts! You have 7 unread messages.",
    "favoriteFruit": "apple"
  },
  {
    "_id": "5e481849f949b442c8d91fdc",
    "index": 21,
    "guid": "d0809df1-2cb1-4e94-9f03-c7a9fa2152f5",
    "isActive": true,
    "balance": "$3,561.79",
    "picture": "http://placehold.it/32x32",
    "age": 25,
    "eyeColor": "brown",
    "name": {
      "first": "Huffman",
      "last": "Carlson"
    },
    "company": "PORTICA",
    "email": "huffman.carlson@portica.net",
    "phone": "+1 (962) 434-2259",
    "address": "619 Summit Street, Florence, Missouri, 3543",
    "about": "Pariatur aliquip cillum et occaecat qui nostrud laboris. Minim adipisicing cupidatat laborum laboris veniam do magna proident excepteur. Aute irure non ex aliquip sit voluptate proident est Lorem ullamco esse aliquip. Eu aliquip officia nostrud eu exercitation.",
    "registered": "Tuesday, June 21, 2016 1:46 PM",
    "latitude": "-8.45309",
    "longitude": "-22.639363",
    "tags": [
      "veniam",
      "magna",
      "sunt",
      "ipsum",
      "id"
    ],
    "range": [
      0,
      1,
      2,
      3,
      4,
      5,
      6,
      7,
      8,
      9
    ],
    "friends": [
      {
        "id": 0,
        "name": "Rush Kelly"
      },
      {
        "id": 1,
        "name": "Ramos Lang"
      },
      {
        "id": 2,
        "name": "Marion Dickerson"
      }
    ],
    "greeting": "Hello, Huffman! You have 5 unread messages.",
    "favoriteFruit": "strawberry"
  },
  {
    "_id": "5e481849dda83eeef9a2e784",
    "index": 22,
    "guid": "6b53c5d1-67eb-43b4-b1de-0e123314d689",
    "isActive": true,
    "balance": "$3,034.56",
    "picture": "http://placehold.it/32x32",
    "age": 28,
    "eyeColor": "blue",
    "name": {
      "first": "Woodward",
      "last": "Cruz"
    },
    "company": "VIRXO",
    "email": "woodward.cruz@virxo.co.uk",
    "phone": "+1 (800) 461-3108",
    "address": "921 Henderson Walk, Jacumba, North Dakota, 7316",
    "about": "Laborum laboris dolore officia labore adipisicing. Enim dolor enim mollit ullamco elit officia aliquip cupidatat ut pariatur consequat minim irure. Aliqua laboris veniam nostrud non cillum. Tempor velit nostrud aute officia esse sunt velit aute amet ut. Est ex reprehenderit in laboris Lorem mollit ullamco cupidatat ipsum aliquip nulla.",
    "registered": "Friday, February 2, 2018 4:00 PM",
    "latitude": "13.827122",
    "longitude": "15.544693",
    "tags": [
      "qui",
      "ea",
      "et",
      "id",
      "dolore"
    ],
    "range": [
      0,
      1,
      2,
      3,
      4,
      5,
      6,
      7,
      8,
      9
    ],
    "friends": [
      {
        "id": 0,
        "name": "House Cunningham"
      },
      {
        "id": 1,
        "name": "Lara Austin"
      },
      {
        "id": 2,
        "name": "Alexander Parrish"
      }
    ],
    "greeting": "Hello, Woodward! You have 5 unread messages.",
    "favoriteFruit": "strawberry"
  },
  {
    "_id": "5e481849008dfda7fb95272d",
    "index": 23,
    "guid": "292d4ec9-f184-4f17-a528-82d360f22c42",
    "isActive": true,
    "balance": "$2,807.39",
    "picture": "http://placehold.it/32x32",
    "age": 30,
    "eyeColor": "green",
    "name": {
      "first": "Clemons",
      "last": "Hatfield"
    },
    "company": "COMVERGES",
    "email": "clemons.hatfield@comverges.biz",
    "phone": "+1 (810) 565-2933",
    "address": "777 Strauss Street, Fivepointville, Utah, 300",
    "about": "Dolore eu nisi officia adipisicing sit dolore ut culpa. Ea irure consectetur sint deserunt ad consectetur ex est anim in. Veniam Lorem eu duis sit tempor est ex dolore. Occaecat officia quis tempor aliqua qui.",
    "registered": "Wednesday, July 17, 2019 4:29 PM",
    "latitude": "-36.686938",
    "longitude": "156.091644",
    "tags": [
      "commodo",
      "excepteur",
      "sit",
      "qui",
      "sit"
    ],
    "range": [
      0,
      1,
      2,
      3,
      4,
      5,
      6,
      7,
      8,
      9
    ],
    "friends": [
      {
        "id": 0,
        "name": "Benson Sweet"
      },
      {
        "id": 1,
        "name": "Pennington Swanson"
      },
      {
        "id": 2,
        "name": "Brown Cantu"
      }
    ],
    "greeting": "Hello, Clemons! You have 8 unread messages.",
    "favoriteFruit": "strawberry"
  },
  {
    "_id": "5e481849960294b64e62fb36",
    "index": 24,
    "guid": "4ca8e955-510d-4fb5-9976-b5bc1085129d",
    "isActive": true,
    "balance": "$1,356.18",
    "picture": "http://placehold.it/32x32",
    "age": 33,
    "eyeColor": "blue",
    "name": {
      "first": "Madelyn",
      "last": "Neal"
    },
    "company": "LYRICHORD",
    "email": "madelyn.neal@lyrichord.name",
    "phone": "+1 (807) 443-3522",
    "address": "760 Greene Avenue, Mansfield, Maryland, 4284",
    "about": "Culpa eu eu mollit sint adipisicing amet fugiat ea qui ad velit irure quis. Deserunt dolor laboris mollit nulla veniam culpa enim ullamco. Excepteur id occaecat ea sint aliqua ullamco Lorem excepteur Lorem. Nostrud nisi aliquip sit consequat dolore laboris exercitation sunt duis.",
    "registered": "Thursday, January 1, 2015 8:22 PM",
    "latitude": "-47.178162",
    "longitude": "-126.978054",
    "tags": [
      "est",
      "et",
      "qui",
      "et",
      "excepteur"
    ],
    "range": [
      0,
      1,
      2,
      3,
      4,
      5,
      6,
      7,
      8,
      9
    ],
    "friends": [
      {
        "id": 0,
        "name": "Rosalind Glenn"
      },
      {
        "id": 1,
        "name": "Callie Holloway"
      },
      {
        "id": 2,
        "name": "Brock Tyson"
      }
    ],
    "greeting": "Hello, Madelyn! You have 7 unread messages.",
    "favoriteFruit": "strawberry"
  },
  {
    "_id": "5e4818492e30fea30a6117c2",
    "index": 25,
    "guid": "1422e2e9-2988-4945-912d-67a3a60b9e17",
    "isActive": true,
    "balance": "$2,964.33",
    "picture": "http://placehold.it/32x32",
    "age": 32,
    "eyeColor": "brown",
    "name": {
      "first": "Liza",
      "last": "Holland"
    },
    "company": "SENTIA",
    "email": "liza.holland@sentia.tv",
    "phone": "+1 (848) 589-2600",
    "address": "182 Anthony Street, Lowgap, Tennessee, 9639",
    "about": "Nisi fugiat eiusmod ad et consectetur dolor ipsum ullamco ad sunt. Velit proident id consequat cillum. Occaecat tempor minim excepteur incididunt occaecat proident voluptate veniam velit officia aliquip. Reprehenderit et minim sint eiusmod ad cupidatat adipisicing. Esse amet enim enim culpa nostrud occaecat reprehenderit. Enim cillum enim adipisicing est labore est aliqua et sit consectetur incididunt labore.",
    "registered": "Saturday, December 31, 2016 4:21 PM",
    "latitude": "17.950551",
    "longitude": "74.338243",
    "tags": [
      "id",
      "esse",
      "esse",
      "sint",
      "commodo"
    ],
    "range": [
      0,
      1,
      2,
      3,
      4,
      5,
      6,
      7,
      8,
      9
    ],
    "friends": [
      {
        "id": 0,
        "name": "Harrington Melton"
      },
      {
        "id": 1,
        "name": "Estrada Grant"
      },
      {
        "id": 2,
        "name": "Marcie Leon"
      }
    ],
    "greeting": "Hello, Liza! You have 5 unread messages.",
    "favoriteFruit": "strawberry"
  },
  {
    "_id": "5e4818495c4329fd9b5f8571",
    "index": 26,
    "guid": "b93cdfa4-3f2c-4159-868e-239f36ff5796",
    "isActive": false,
    "balance": "$3,668.80",
    "picture": "http://placehold.it/32x32",
    "age": 30,
    "eyeColor": "blue",
    "name": {
      "first": "Nicole",
      "last": "Potts"
    },
    "company": "CENTREE",
    "email": "nicole.potts@centree.biz",
    "phone": "+1 (949) 400-2887",
    "address": "723 Corbin Place, Chamberino, Oregon, 4921",
    "about": "Occaecat sint aute excepteur deserunt Lorem cupidatat laboris ad irure nulla incididunt. Nostrud aute dolor aliqua ipsum exercitation amet esse minim. Eiusmod amet veniam cupidatat laboris enim esse incididunt. Pariatur quis do duis tempor. Exercitation nostrud eiusmod ea duis dolor Lorem aliquip duis velit anim eu ex nostrud pariatur.",
    "registered": "Friday, March 23, 2018 5:52 AM",
    "latitude": "-64.05546",
    "longitude": "-152.992192",
    "tags": [
      "amet",
      "non",
      "duis",
      "aliqua",
      "in"
    ],
    "range": [
      0,
      1,
      2,
      3,
      4,
      5,
      6,
      7,
      8,
      9
    ],
    "friends": [
      {
        "id": 0,
        "name": "Tara Lott"
      },
      {
        "id": 1,
        "name": "Jimmie Chapman"
      },
      {
        "id": 2,
        "name": "Kidd Mccormick"
      }
    ],
    "greeting": "Hello, Nicole! You have 5 unread messages.",
    "favoriteFruit": "strawberry"
  },
  {
    "_id": "5e4818497b30fd8c1f1c885e",
    "index": 27,
    "guid": "c6257d78-3109-4a98-8687-3347222a0837",
    "isActive": false,
    "balance": "$2,143.37",
    "picture": "http://placehold.it/32x32",
    "age": 31,
    "eyeColor": "green",
    "name": {
      "first": "Finley",
      "last": "Huber"
    },
    "company": "CONFRENZY",
    "email": "finley.huber@confrenzy.info",
    "phone": "+1 (891) 561-2771",
    "address": "948 Halleck Street, Hachita, Ohio, 3425",
    "about": "Ex magna enim quis sunt mollit id dolor est officia commodo irure voluptate velit eu. In irure ea minim amet consequat ullamco eu id. Commodo velit Lorem minim elit nulla eu aute ex sint. Sint proident fugiat sit anim esse. Laboris et et velit laboris anim laboris laborum. Amet minim ex et ad ad incididunt ad tempor nostrud aute.",
    "registered": "Thursday, June 28, 2018 9:32 AM",
    "latitude": "63.077473",
    "longitude": "69.708487",
    "tags": [
      "excepteur",
      "exercitation",
      "irure",
      "amet",
      "pariatur"
    ],
    "range": [
      0,
      1,
      2,
      3,
      4,
      5,
      6,
      7,
      8,
      9
    ],
    "friends": [
      {
        "id": 0,
        "name": "Bonnie Maynard"
      },
      {
        "id": 1,
        "name": "Anastasia Rollins"
      },
      {
        "id": 2,
        "name": "Guerrero Allen"
      }
    ],
    "greeting": "Hello, Finley! You have 9 unread messages.",
    "favoriteFruit": "strawberry"
  },
  {
    "_id": "5e48184922505b03c6c3fe15",
    "index": 28,
    "guid": "f74b5fe9-d3e8-403a-956b-19ddef4290e6",
    "isActive": true,
    "balance": "$3,972.36",
    "picture": "http://placehold.it/32x32",
    "age": 20,
    "eyeColor": "green",
    "name": {
      "first": "Gilbert",
      "last": "Dominguez"
    },
    "company": "ZYTRAX",
    "email": "gilbert.dominguez@zytrax.com",
    "phone": "+1 (866) 542-3342",
    "address": "216 Doughty Street, Westboro, South Carolina, 6127",
    "about": "Ad non exercitation ex mollit do Lorem mollit commodo sit dolore. Consectetur eiusmod velit consectetur esse aliqua ex enim non id esse. Laboris non veniam quis minim non veniam culpa culpa deserunt reprehenderit. Veniam proident consectetur cillum minim nisi incididunt consectetur amet veniam.",
    "registered": "Saturday, October 13, 2018 5:42 AM",
    "latitude": "70.378479",
    "longitude": "9.674162",
    "tags": [
      "ad",
      "laboris",
      "magna",
      "est",
      "sunt"
    ],
    "range": [
      0,
      1,
      2,
      3,
      4,
      5,
      6,
      7,
      8,
      9
    ],
    "friends": [
      {
        "id": 0,
        "name": "Castaneda Mccall"
      },
      {
        "id": 1,
        "name": "Leanne Crawford"
      },
      {
        "id": 2,
        "name": "Melanie Brown"
      }
    ],
    "greeting": "Hello, Gilbert! You have 6 unread messages.",
    "favoriteFruit": "strawberry"
  }
]